[
  {
    "pageid": "7",
    "backgroudimage": "/background2.jpg",
    "unitTitles": {
      "Unittitle": "حُرُوفُ الْهِجَاءِ الْعَرَبِيِّةِ",
      "unitname": "أَسْمَاءُ الحُرُوفِ",
      "unitnumber": "الوَحْدَةُ الأُولَى"
    },
    "minigames":{
      "title": "العاب حرف القاف",
      "games": [
        { 
          "title": "Fishing",
          "thumbnail_image_url": "minigames/assets/thumbnails/fishingThumb.png", 
          "jsonFile": "136_fishing.json"
        },
        { 
          "title": "Airplane",
          "thumbnail_image_url": "minigames/assets/thumbnails/planeThumb.png", 
          "jsonFile": "136_airplane.json"
        },
        { 
          "title": "Apple Tree",
          "thumbnail_image_url": "minigames/assets/thumbnails/treeThumb.png", 
          "jsonFile": "136_AppleTree.json"
        }
      ]
    },
    "exercisenames": [
      "U2QuranPhaser"
    ],
    "exersices": [
      {
        "type": "U2QuranPhaser",
        "display": "column",
        "layout": {
          "direction": "vertical",
          "fit": "full"
        },
        "board": "/frame_board.png",
        "titles": {
          "id": "2",
          "titlearabic": ".اِسْتَمِعْ، ثُمَّ ضَعْ خَطًّا تَحْتَ أَشْكَالِ حَرْفِ القَافِ",
          "titleenglish": "Listen and underline the shapes of the letter (ق).",
          "audio": "pagetitleaudios/137/1.mp3",
          "fontsize": "1.1vh"
        },
        "size": {
          "gridcol": "span 2",
          "gridrow": "2/5",
          "offsetY":"7%",
          "scaleY":"0.9"
        },
        "path": "/quran_audio/7/",
        "letter":"ا",
        "questionIndex": 3,
        "questions": [
          {
            "quranaudio": "a1-137",
    "ayaverse": "سورة البقرة آية 19",
    "ayaverseEnglish": "Surah Al-Baqarah Verse 19",
             "otherAreas": [   
              {  "letter": "بـ", "x": 717, "y": 644, "w": 72, "h": 187,  "message":"!اختر الشكل المنفصل", "alpha": 1, "fontsize": 95,"color": "#DB2A50", "isTarget": true } 
            ],
            "frames": [
              {"key": "1-1-137", "x": 740,"y": 420,"w": 860,"h": 170,"time": 11000,"fontsize": 80 },
              {"key": "1-2-137", "x": 740,"y": 620,"w": 860,"h": 140,"time": 2000,"fontsize": 80 } 
            ]
          }, 
          {
            "quranaudio": "a2-137",
    "ayaverse": "سورة ق آية 37",
    "ayaverseEnglish": "Surah Qaf Verse 37",
             "otherAreas": [ 
              {  "letter": "بـ", "x": 402, "y": 450, "w": 41, "h": 160,  "message":"!اختر الشكل المنفصل", "alpha": 1, "fontsize": 95,"color": "#DB2A50", "isTarget": true } 
            ],
            "frames": [
              {"key": "2-1-137", "x": 740,"y": 420,"w": 1200,"h": 155,"time": 12000,"fontsize": 80 }, 
              {"key": "2-2-137", "x": 743,"y": 620,"w": 1200,"h": 150,"time": 5000,"fontsize": 80 } 
            ]
          }, 
          {
            "quranaudio": "a3-137",
    "ayaverse": "سورة البقرة آية 69",
    "ayaverseEnglish": "Surah Al-Baqarah Verse 69",
             "otherAreas": [ 
              {  "letter": "بـ", "x": 1212, "y": 548, "w": 42, "h": 150,  "message":"!اختر الشكل المنفصل", "alpha": 1, "fontsize": 95,"color": "#DB2A50", "isTarget": true } 
            ],
            "frames": [
              {"key": "3-1-137", "x": 739,"y": 520,"w": 1360,"h": 150,"time": 18000,"fontsize": 80 } 
            ]
          },
          {
            "quranaudio": "a4-137",
    "ayaverse": "سورة الشعراء آية 100 - 101",
    "ayaverseEnglish": "Surah Ash-Shu'ara Verses 100-101",
             "otherAreas": [  
              {  "letter": "بـ", "x": 386, "y": 589, "w": 60, "h": 150,  "message":"!اختر الشكل المنفصل", "alpha": 1, "fontsize": 95,"color": "#DB2A50", "isTarget": true }
            ],
            "frames": [
              {"key": "4-1-137", "x": 740,"y":530,"w": 1360,"h": 145,"time": 15000,"fontsize": 80 } 
            ]
          } 
        ]
      }       ,{
                "type": "PhaserSequencePlayer",
                "display": "column",
        "titles": {
          "id": "2",
          "titlearabic": ".اِقْرَأْ أَسْمَاءَ الحُرُوفِ التَّالِيَةِ.",
          "titleenglish": "Pronounce the following letter.",
          "audio": "pagetitleaudios/87/2.mp3",
          "delay": 2000,
          "fontsize": "1.1vh"
        },
                "gametitles": [ 
                ],
        "size": {
          "gridcol": "span 2",
          "gridrow": "5/6",
          "offsetY":"-2%",
          "scaleY":"0.7"
        },
                "path": "/letters_page/",
                "questions": [
                    {
                        "pieces": [
                            {"x": 1304,"y":490,"w": 250,"key": "asH1137", "audio":"asH1A137","correctDropZone": "dz4","scale": "4","color": "#D72343","float": false,"fontSize": "200px","fontFamily": "quranic"},
                            {"x": 1025,"y":490,"w": 250,"key": "asH2137", "audio":"asH2A137","correctDropZone": "dz4","scale": "4","color": "#D72343","float": false,"fontSize": "200px","fontFamily": "quranic"},
                            {"x": 745, "y": 490,"w": 250,"key": "asH3137", "audio":"asH3A137","correctDropZone": "dz4","scale": "4","color": "#D72343","float": false,"fontSize": "200px","fontFamily": "quranic"},
                            {"x": 464, "y": 490,"w": 250,"key": "asH4137", "audio":"asH4A137","correctDropZone": "dz4","scale": "4","color": "#D72343","float": false,"fontSize": "200px","fontFamily": "quranic"},
                            {"x": 182, "y": 490,"w": 250,"key": "asH5137", "audio":"asH5A137","correctDropZone": "dz4","scale": "4","color": "#D72343","float": false,"fontSize": "200px","fontFamily": "quranic"} 
                        ],
                        "frames": [ 
                        ]
                    }
                ]
            }
    ]
  }
]